Workbook
Name FID_1: [1]AGR_Fuels!$A$2

Sheet SEC_Comm
B2: Define Commodities
B4: ~FI_Comm
B5: Csets | C5: CommName | D5: CommDesc | E5: Unit | F5: LimType | G5: CTSLvl | H5: PeakTS | I5: Ctype
B6: \I: Commodity Set | C6: Commodity Name | D6: Commodity Description | E6: Unit | F6: Sense of Balance Equation | G6: TimeSlice Level | H6: Peak Monitoring | I6: Electricity Indicator (for CHPs)
B7: \I: Predefiniowany zbiór dóbr | C7: Nazwa dobra | D7: Opis sobra | E7: Jednostka dobra | F7: - | G7: Poziom podokresów roku - równanie bilansu | H7: - | I7: Oznaczenie dobra "energia elektryczna" dla CHP
B8: NRG | C8: HC | D8: Hard Coal | E8: PJ
B9: NRG | C9: BC | D9: Brown Coal/Lignite | E9: PJ
B10: NRG | C10: NAT-GAS | D10: Natural Gas | E10: PJ
B11: NRG | C11: WIND-ON | D11: Onshore Wind Energy | E11: PJ
B12: NRG | C12: SOLAR | D12: Solar Energy | E12: PJ
B16: Available Commodity Sets
B17: NRG | C17: Energy
B18: ENV | C18: Emission
B19: DEM | C19: Demand
B20: MAT | C20: Material
B21: FIN | C21: Financial

Sheet SEC_Processes
B2: Define Processes
B4: ~FI_Process
B5: Sets | C5: Region | D5: TechName | E5: TechDesc | F5: Tact | G5: Tcap | H5: Tslvl | I5: PrimaryCG | J5: Vintage
B6: \I: Process Set | C6: Region Name | D6: Technology Name | E6: Technology Description | F6: Activity Unit | G6: Capacity Unit | H6: TimeSlice Level | I6: Primary Commodity Group | J6: Vintage Tracking
B7: \I: Predefiniowany zbiór procesów | C7: Nazwa regionu | D7: Nazwa procesu | E7: Opis procesu | F7: Jednostka aktywności procesu | G7: Jednostka mocy zainstalowanej procesu | H7: Poziom podokresów roku - równanie bilansu
B8: MIN | C8: PL | D8: MIN_HC | E8: Hard Coal Domestic Supply | F8: PJ
B9: MIN | C9: PL | D9: MIN_BC | E9: Brown Coal Domestic Supply | F9: PJ
B10: MIN | C10: PL | D10: MIN_NAT-GAS | E10: Natural Gas Domestic Supply | F10: PJ | L10: <- supply of natural gas from two different sources
B11: IMP | C11: PL | D11: IMP_NAT-GAS | E11: Natural Gas Imports | F11: PJ
B12: MIN | C12: PL | D12: MIN_WIND-ON | E12: Wind Onshore | F12: PJ
B13: MIN | C13: PL | D13: MIN_SOLAR | E13: Solar | F13: PJ
B17: Available Process Sets
B18: ELE | C18: Power Plant (Electricity Only)
B19: CHP | C19: Combined Heat & Power Plant
B20: STG | C20: Timeslice Storage
B21: PRE | C21: Generic Process
B22: DMD | C22: Demand Process | D22: Demand Type Commodity at Output
B23: IMP | C23: Import | D23: Commodity only at Output
B24: EXP | C24: Eksport | D24: Commodity only at Input
B25: MIN | C25: Mining | D25: Commodity only at Output
B26: HPL | C26: Heat Only Plant

Sheet MIN_IMP
B2: Primary Energy Carriers Extraction | N2: Very Long Table
B4: ~FI_T
B5: TechName | C5: * TechDesc | D5: Comm-OUT | E5: COST | F5: ACT_BND~UP | G5: ACT_BND~FX | H5: ACT_BND~LO | N5: TechName | O5: * TechDesc | P5: Comm-OUT | Q5: COST~2020 | R5: COST~2025 | S5: COST~2030 | T5: COST~2035 | U5: COST~2040 | V5: COST~2045 | W5: COST~2050 | X5: ACT_BND~UP~2020 | Y5: ACT_BND~UP~2025 | Z5: ACT_BND~UP~2030 | AA5: ACT_BND~UP~2035 | AB5: ACT_BND~UP~2040 | AC5: ACT_BND~UP~2045 | AD5: ACT_BND~UP~2050 | AE5: ACT_BND~LO~2020 | AF5: ACT_BND~LO~2025 | AG5: ACT_BND~LO~2030 | AH5: ACT_BND~LO~2035 | AI5: ACT_BND~LO~2040 | AJ5: ACT_BND~LO~2045 | AK5: ACT_BND~LO~2050
B6: \I: Technology Name | C6: Technology Description | D6: Output Commodity | E6: Extraction Cost [MPLN/PJ] | F6: Annual Extraction Upper Bound [PJ/a] | G6: Annual Extraction Fixed Bound [PJ/a] | H6: Annual Extraction Lower Bound [PJ/a] | J6: -> Example of assignment of attribute values in all model years (cumbersome to maintain) | N6: \I: Technology Name | O6: Technology Description | P6: Output Commodity | Q6: Extraction Cost [MPLN/PJ] | X6: Annual Extraction Upper Bound [PJ/a] | AE6: Annual Extraction Lower Bound [PJ/a]
B7: \I: Nazwa procesu | C7: Opis procesu | D7: Dobro na wyjściu | E7: Koszt wydobycia (loco kopalnia) | F7: Ograniczenie wydobycia w roku (≤) | G7: Wymuszenie wydobycia w roku (=) | H7: Ograniczenie wydobycia w roku (≥) | N7: \I: Nazwa procesu | O7: Opis procesu | P7: Dobro na wyjściu | Q7: Koszt wydobycia (loco kopalnia) | X7: Ograniczenie wydobycia w roku (≤) | AE7: Ograniczenie wydobycia w roku (≥)
B8: =SEC_Processes!D8 -> MIN_HC | C8: =SEC_Processes!E8 -> Hard Coal Domestic Supply | D8: =SEC_Comm!C8 -> HC | E8: 15 | J8: <- Only baseline price here. Actual forecast of fuel prices in future years is in the scenario file "FUEL_PRICE_PROJ". | N8: =B8 -> MIN_HC | O8: =C8 -> Hard Coal Domestic Supply | P8: =D8 -> HC | Q8: 15 | R8: =Q8*1.02 -> 15.3 | S8: =R8*1.02 -> 15.606 | T8: =S8*1.02 -> 15.91812 | U8: =T8*1.02 -> 16.236482 | V8: =U8*1.02 -> 16.561212 | W8: =V8*1.02 -> 16.892436
B9: =SEC_Processes!D9 -> MIN_BC | C9: =SEC_Processes!E9 -> Brown Coal Domestic Supply | D9: =SEC_Comm!C9 -> BC | E9: 7 | N9: =B9 -> MIN_BC | O9: =C9 -> Brown Coal Domestic Supply | P9: =D9 -> BC | Q9: 7 | R9: =Q9*1.01 -> 7.07 | S9: =R9*1.01 -> 7.1407 | T9: =S9*1.01 -> 7.212107 | U9: =T9*1.01 -> 7.2842281 | V9: =U9*1.01 -> 7.3570704 | W9: =V9*1.01 -> 7.4306411
B10: =SEC_Processes!D10 -> MIN_NAT-GAS | C10: =SEC_Processes!E10 -> Natural Gas Domestic Supply | D10: =SEC_Comm!C10 -> NAT-GAS | E10: 28 | N10: =B10 -> MIN_NAT-GAS | O10: =C10 -> Natural Gas Domestic Supply | P10: =D10 -> NAT-GAS | Q10: 28 | R10: =Q10*1.03 -> 28.84 | S10: =R10*1.03 -> 29.7052 | T10: =S10*1.03 -> 30.596356 | U10: =T10*1.03 -> 31.514247 | V10: =U10*1.03 -> 32.459674 | W10: =V10*1.03 -> 33.433464
B11: =SEC_Processes!D11 -> IMP_NAT-GAS | C11: =SEC_Processes!E11 -> Natural Gas Imports | D11: =SEC_Comm!C10 -> NAT-GAS | E11: 30 | N11: =B11 -> IMP_NAT-GAS | O11: =C11 -> Natural Gas Imports | P11: =D11 -> NAT-GAS | Q11: 30 | R11: =Q11*0.99 -> 29.7 | S11: =R11*0.99 -> 29.403 | T11: =S11*0.99 -> 29.10897 | U11: =T11*0.99 -> 28.81788 | V11: =U11*0.99 -> 28.529701 | W11: =V11*0.99 -> 28.244404
B12: =SEC_Processes!D12 -> MIN_WIND-ON | C12: =SEC_Processes!E12 -> Wind Onshore | D12: =SEC_Comm!C11 -> WIND-ON | E12: 0.001 | N12: =B12 -> MIN_WIND-ON | O12: =C12 -> Wind Onshore | P12: =D12 -> WIND-ON | Q12: 0.001 | R12: 0.001 | S12: 0.001 | T12: 0.001 | U12: 0.001 | V12: 0.001 | W12: 0.001
B13: =SEC_Processes!D13 -> MIN_SOLAR | C13: =SEC_Processes!E13 -> Solar | D13: =SEC_Comm!C12 -> SOLAR | E13: 0.001 | N13: =B13 -> MIN_SOLAR | O13: =C13 -> Solar | P13: =D13 -> SOLAR | Q13: 0.001 | R13: 0.001 | S13: 0.001 | T13: 0.001 | U13: 0.001 | V13: 0.001 | W13: 0.001
B17: Alternative syntax with LimType Attribute
B19: TechName | C19: * TechDesc | D19: Comm-OUT | E19: COST | F19: LimType | G19: ACT_BND
B20: \I: Technology Name | C20: Technology Description | D20: Output Commodity | E20: Extraction Cost [MPLN/PJ] | F20: Attribute Sign | G20: Annual Extraction Fixed Bound [PJ]
B21: \I: Nazwa procesu | C21: Opis procesu | D21: Dobro na wyjściu | E21: Koszt wydobycia (loco kopalnia) | F21: Znak ograniczenia UP ≤ FX = LO ≥ | G21: Wymuszenie wydobycia w roku (=)
B22: =B8 -> MIN_HC | C22: =C8 -> Hard Coal Domestic Supply | D22: =D8 -> HC | E22: =E8 -> 15 | F22: UP
F23: FX
F24: LO
B25: =B9 -> MIN_BC | C25: =C9 -> Brown Coal Domestic Supply | D25: =D9 -> BC | E25: =E9 -> 7
B26: =B10 -> MIN_NAT-GAS | C26: =C10 -> Natural Gas Domestic Supply | D26: =D10 -> NAT-GAS | E26: =E10 -> 28
B27: =B11 -> IMP_NAT-GAS | C27: =C11 -> Natural Gas Imports | D27: =D11 -> NAT-GAS | E27: =E11 -> 30
B28: =B12 -> MIN_WIND-ON | C28: =C12 -> Wind Onshore | D28: =D12 -> WIND-ON | E28: =E12 -> 0.001
B29: =B13 -> MIN_SOLAR | C29: =C13 -> Solar | D29: =D13 -> SOLAR | E29: =E13 -> 0.001
